swsh/buy_a_phone_number.py
swsh/functions.py
swsh/swsh.py
swsh-0.1.14.dist-info/METADATA
swsh-0.1.14.dist-info/WHEEL
swsh-0.1.14.dist-info/entry_points.txt
swsh-0.1.14.dist-info/top_level.txt
swsh-0.1.14.dist-info/RECORD
