Metadata-Version: 2.1
Name: swsh
Version: 0.1.14
Summary: SignalWire interactive SHell
Home-page: https://github.com/signalwire/swsh
Author: Shane Harrell
Author-email: shane.harrell@signalwire.com
License: MIT
Classifier: Development Status :: 5 - Production/Stable
Classifier: Intended Audience :: Developers
Classifier: Intended Audience :: Information Technology
Classifier: Intended Audience :: Telecommunications Industry
Classifier: License :: OSI Approved :: MIT License
Classifier: Natural Language :: English
Classifier: Topic :: Communications
Classifier: Topic :: Software Development
Requires-Python: >=3.6
Requires-Dist: signalwire
Requires-Dist: requests
Requires-Dist: python-dotenv
Requires-Dist: cmd2
Requires-Dist: pyvim
Requires-Dist: gnureadline ; platform_system == "Darwin"
